{
  "name": "Spirit Wood Staff",
  "advancement": "magickcore:learn/wand",
  "icon": "magickcore:staff",
  "category": "magickcore:spirit_product",
  "pages": [
    {
      "type": "text",
      "text": "The spirit wood staff itself does not carry any spells, can release magick directly without charging, and a Magick Context can be equipped. You can craft a spirit wood staff by combining a magick context and a spirit wood staff at a workbench. A spirit wood staff with a magick context can be used as a crafting ingredient to extract the magick context."
    },
    {
      "type": "magickcore:magick_recipe",
      "magick_recipe": "magickcore:spirit_wood_staff",
      "text": "Crafted at the Magic Workbench."
    }
  ]
}