{
  "name": "Wither Element",
  "advancement": "magickcore:learn/wither",
  "icon": "magickcore:wither",
  "category": "element",
  "pages": [
    {
      "type": "spotlight",
	  "item": "magickcore:wither",
      "text": "Wither Element is born from drak，it's a element suppression of the target。$(br2)Wither element makes target brief bleeding，但不会击杀目标。也可以限制目标最大回血量，使其无法达到满血状态。"
    },
	{
      "type": "text",
	  "title": " ",
      "text": "超能状态的枯萎元素会在符文中间形成一个枯萎球体，对非友军单位释放牵引线，对目标造成血量限制和持续流血效果。"
    }
  ]
}